kubeasy.py
config/__init__.py
config/_cmds.py
config/_config.py
core/__init__.py
core/configurator.py
kubeasy-0.1.dist-info/DESCRIPTION.rst
kubeasy-0.1.dist-info/METADATA
kubeasy-0.1.dist-info/RECORD
kubeasy-0.1.dist-info/WHEEL
kubeasy-0.1.dist-info/entry_points.txt
kubeasy-0.1.dist-info/metadata.json
kubeasy-0.1.dist-info/top_level.txt
